earthos/__init__.py
earthos/earthos.py
earthos/eoformula.py
earthos/eoimage.py
earthos/eoregion.py
tests/__init__.py
tests/test_colorscales.py
tests/test_formulas.py
tests/test_point.py
tests/test_regions.py
tests/test_variables.py
earthos-0.1.2.dist-info/LICENSE
earthos-0.1.2.dist-info/METADATA
earthos-0.1.2.dist-info/WHEEL
earthos-0.1.2.dist-info/top_level.txt
earthos-0.1.2.dist-info/RECORD
