Metadata-Version: 2.1
Name: earthos
Version: 0.1.2
Summary: Ecosophy EarthOS API bindings
Home-page: https://ecosophy.is/
Author: Ecosophy
Author-email: info@ecosophy.is
License: Apache
Classifier: Development Status :: 4 - Beta
Classifier: Intended Audience :: Developers
Classifier: Intended Audience :: Science/Research
Classifier: License :: OSI Approved :: Apache Software License
Classifier: Operating System :: OS Independent
Classifier: Programming Language :: Python :: 3
Classifier: Topic :: Software Development :: Libraries :: Python Modules
Classifier: Topic :: Scientific/Engineering :: Atmospheric Science
Classifier: Topic :: Scientific/Engineering :: Oceanography
License-File: LICENSE
Requires-Dist: requests
Requires-Dist: Pillow
Requires-Dist: numpy
